django_orm_views/__init__.py
django_orm_views/apps.py
django_orm_views/constants.py
django_orm_views/exceptions.py
django_orm_views/not_managed_model.py
django_orm_views/register.py
django_orm_views/sync.py
django_orm_views/views.py
django_orm_views/management/__init__.py
django_orm_views/management/commands/__init__.py
django_orm_views/management/commands/sync_views.py
django_orm_views-2.0.3.dist-info/LICENSE
django_orm_views-2.0.3.dist-info/METADATA
django_orm_views-2.0.3.dist-info/WHEEL
django_orm_views-2.0.3.dist-info/top_level.txt
django_orm_views-2.0.3.dist-info/RECORD
