Metadata-Version: 2.1
Name: django-orm-views
Version: 2.0.3
Summary: A framework for managing database views based on Django, without the migrations
Author: iwoca
Author-email: Josh Dutton <j.dutton@iwoca.co.uk>
License: Copyright 2022 iwoca Ltd
Project-URL: Homepage, https://github.com/iwoca/django-orm-views
Project-URL: Bug Tracker, https://github.com/iwoca/django-orm-views/issues
Classifier: Programming Language :: Python :: 3
Classifier: License :: OSI Approved :: MIT License
Classifier: Operating System :: OS Independent
Requires-Python: >=3.6
License-File: LICENSE
Provides-Extra: test
Requires-Dist: psycopg2-binary ==2.8.6 ; extra == 'test'
